<?xml version="1.0" encoding="UTF-8"?>
<dataset>
    <responsavel id="1" nome="Livia Costa Carvalho" senhadigital="Oughh8ux" />
    <responsavel id="2" nome="Erick Lima Barros" senhadigital="ONgu9eiZ8" />
    <responsavel id="3" nome="Alex Santos Sousa" senhadigital="Oowai4Hoyai" />
    <responsavel id="4" nome="Maria Cunha Pinto" senhadigital="Ecorao5loo" />
    <responsavel id="5" nome="Bruno Oliveira Castro" senhadigital="cahn8Ko4soh" />
    <responsavel id="6" nome="Lavinia Barbosa Goncalves" senhadigital="eixai2Taech" />
    <responsavel id="7" nome="Nicole Goncalves Castro" senhadigital="oJieng1ee" />
    <responsavel id="8" nome="Beatrice Araujo Gomes" senhadigital="Choh5Ou5ue" />
    <responsavel id="9" nome="Murilo Carvalho Barros" senhadigital="pheiL7wee2O" />
    <responsavel id="10" nome="André Costa Azevedo" senhadigital="Ookaechie2" />
    
    <departamento id="7" nome="Pro-reitoria de pesquisa" sigla="PROPESQ" id_responsavel="7"  />    
    <departamento id="8" nome="Diretoria de gestão de pessoas" sigla="DGPE" id_responsavel="8"  />
    <departamento id="6" nome="Serviço Social - Psicologia" sigla="PSCICOL" id_responsavel="6"  />

    <processo id="1" nome="Solicitação de comprovante de matrícula" id_responsavel="1" duracaoMaximaEmDias="5" />
    
       <atividade id="1" nome="Solicitação da aprovação pela biblioteca" situacao="EmEspera"
                  id_processo="1" id_departamento="6"    />
       <atividade id="2" nome="Liberação do requerimento" situacao="EmEspera"
                  id_processo="1" id_departamento="5"    />
       <atividade id="3" nome="Solicitação da aprovação da DASE" situacao="EmEspera"
                  id_processo="1" id_departamento="5"    />
    
</dataset>